seawater/__init__.py
seawater/_version.py
seawater/constants.py
seawater/eos80.py
seawater/extras.py
seawater/geostrophic.py
seawater/library.py
seawater-3.3.5.dist-info/LICENSE.CSIRO
seawater-3.3.5.dist-info/LICENSE.txt
seawater-3.3.5.dist-info/METADATA
seawater-3.3.5.dist-info/WHEEL
seawater-3.3.5.dist-info/top_level.txt
seawater-3.3.5.dist-info/RECORD
