Metadata-Version: 2.1
Name: seawater
Version: 3.3.5
Summary: Seawater Library for Python
Maintainer-email: Filipe Fernandes <ocefpaf+seawater@gmail.com>
License: The MIT License (MIT)
Project-URL: documentation, https://pyoceans.github.io/python-seawater
Project-URL: homepage, https://pypi.org/project/seawater/
Project-URL: repository, https://github.com/pyoceans/python-seawater
Classifier: Programming Language :: Python :: 3 :: Only
Classifier: Programming Language :: Python :: 3.8
Classifier: Programming Language :: Python :: 3.9
Classifier: Programming Language :: Python :: 3.10
Classifier: Programming Language :: Python :: 3.11
Classifier: Programming Language :: Python :: 3.12
Requires-Python: >=3.8
License-File: LICENSE.CSIRO
License-File: LICENSE.txt
Requires-Dist: numpy
Requires-Dist: scipy
